{"responses":[{"faceAnnotations":[{"boundingPoly":{"vertices":[{"x":86,"y":148},{"x":206,"y":148},{"x":206,"y":287},{"x":86,"y":287}]},"fdBoundingPoly":{"vertices":[{"x":93,"y":200},{"x":164,"y":200},{"x":164,"y":271},{"x":93,"y":271}]},"landmarks":[{"type":"LEFT_EYE","position":{"x":109.44876,"y":210.08029,"z":0.00051194266}},{"type":"RIGHT_EYE","position":{"x":122.7072,"y":218.28387,"z":-32.217304}},{"type":"LEFT_OF_LEFT_EYEBROW","position":{"x":107.83019,"y":198.28296,"z":9.8514481}},{"type":"RIGHT_OF_LEFT_EYEBROW","position":{"x":106.52768,"y":204.26544,"z":-13.402907}},{"type":"LEFT_OF_RIGHT_EYEBROW","position":{"x":114.0838,"y":208.51912,"z":-29.328838}},{"type":"RIGHT_OF_RIGHT_EYEBROW","position":{"x":129.69653,"y":212.50572,"z":-44.334885}},{"type":"MIDPOINT_BETWEEN_EYES","position":{"x":110.82992,"y":214.09351,"z":-19.436419}},{"type":"NOSE_TIP","position":{"x":102.43983,"y":233.98642,"z":-18.0658}},{"type":"UPPER_LIP","position":{"x":107.8883,"y":247.86032,"z":-11.498708}},{"type":"LOWER_LIP","position":{"x":110.28226,"y":259.44046,"z":-7.3625121}},{"type":"MOUTH_LEFT","position":{"x":110.882,"y":248.46848,"z":6.2380595}},{"type":"MOUTH_RIGHT","position":{"x":119.57488,"y":255.47418,"z":-18.741201}},{"type":"MOUTH_CENTER","position":{"x":110.41038,"y":253.14096,"z":-9.0290966}},{"type":"NOSE_BOTTOM_RIGHT","position":{"x":114.99828,"y":238.92444,"z":-20.810495}},{"type":"NOSE_BOTTOM_LEFT","position":{"x":108.07706,"y":234.5547,"z":-3.4223843}},{"type":"NOSE_BOTTOM_CENTER","position":{"x":108.50613,"y":239.60271,"z":-13.601125}},{"type":"LEFT_EYE_TOP_BOUNDARY","position":{"x":107.18008,"y":207.76366,"z":-1.5964139}},{"type":"LEFT_EYE_RIGHT_CORNER","position":{"x":112.33586,"y":212.0127,"z":-6.5080142}},{"type":"LEFT_EYE_BOTTOM_BOUNDARY","position":{"x":109.12775,"y":212.4053,"z":0.42658415}},{"type":"LEFT_EYE_LEFT_CORNER","position":{"x":109.70447,"y":208.04922,"z":7.6540136}},{"type":"LEFT_EYE_PUPIL","position":{"x":108.4224,"y":209.90996,"z":0.16772237}},{"type":"RIGHT_EYE_TOP_BOUNDARY","position":{"x":121.20235,"y":216.44621,"z":-34.402046}},{"type":"RIGHT_EYE_RIGHT_CORNER","position":{"x":128.21332,"y":220.07729,"z":-37.735706}},{"type":"RIGHT_EYE_BOTTOM_BOUNDARY","position":{"x":122.53278,"y":220.9958,"z":-32.226543}},{"type":"RIGHT_EYE_LEFT_CORNER","position":{"x":120.4556,"y":217.81723,"z":-26.020924}},{"type":"RIGHT_EYE_PUPIL","position":{"x":122.77628,"y":218.83601,"z":-33.50861}},{"type":"LEFT_EYEBROW_UPPER_MIDPOINT","position":{"x":105.00931,"y":197.13614,"z":-3.6242867}},{"type":"RIGHT_EYEBROW_UPPER_MIDPOINT","position":{"x":120.20441,"y":206.54753,"z":-39.159702}},{"type":"LEFT_EAR_TRAGION","position":{"x":142.31123,"y":217.62575,"z":42.129875}},{"type":"RIGHT_EAR_TRAGION","position":{"x":174.22934,"y":237.35701,"z":-32.249516}},{"type":"FOREHEAD_GLABELLA","position":{"x":108.83064,"y":206.09473,"z":-21.910686}},{"type":"CHIN_GNATHION","position":{"x":114.43384,"y":275.74573,"z":-1.0979267}},{"type":"CHIN_LEFT_GONION","position":{"x":129.98531,"y":242.90363,"z":39.109138}},{"type":"CHIN_RIGHT_GONION","position":{"x":158.78151,"y":260.59167,"z":-28.213209}}],"rollAngle":0.13278644,"panAngle":-67.493813,"tiltAngle":-14.733122,"detectionConfidence":0.8376137,"landmarkingConfidence":0.52476674,"joyLikelihood":"VERY_UNLIKELY","sorrowLikelihood":"VERY_UNLIKELY","angerLikelihood":"VERY_UNLIKELY","surpriseLikelihood":"VERY_UNLIKELY","underExposedLikelihood":"VERY_UNLIKELY","blurredLikelihood":"VERY_UNLIKELY","headwearLikelihood":"VERY_UNLIKELY"}],"logoAnnotations":[{"mid":"/m/0czj0s","description":"jimmy choo","score":0.83315003,"boundingPoly":{"vertices":[{"x":11,"y":95},{"x":113,"y":95},{"x":113,"y":233},{"x":11,"y":233}]}}],"labelAnnotations":[{"mid":"/m/07s6nbt","description":"Text","score":0.89724308,"topicality":0.89724308},{"mid":"/m/01f43","description":"Beauty","score":0.88885677,"topicality":0.88885677},{"mid":"/m/03gq5hm","description":"Font","score":0.81951183,"topicality":0.81951183},{"mid":"/m/01n5jq","description":"Poster","score":0.80696958,"topicality":0.80696958},{"mid":"/m/02cwm","description":"Design","score":0.73012,"topicality":0.73012},{"mid":"/m/011s0","description":"Advertising","score":0.72815436,"topicality":0.72815436},{"mid":"/m/030jx3","description":"Square","score":0.58878142,"topicality":0.58878142},{"mid":"/m/01cd9","description":"Brand","score":0.54519564,"topicality":0.54519564},{"mid":"/m/0fc1fy","description":"Black hair","score":0.51658541,"topicality":0.51658541},{"mid":"/m/03c31","description":"Graphic design","score":0.51510304,"topicality":0.51510304}]}]}
