{"responses":[{"faceAnnotations":[{"boundingPoly":{"vertices":[{"x":180,"y":373},{"x":247,"y":373},{"x":247,"y":451},{"x":180,"y":451}]},"fdBoundingPoly":{"vertices":[{"x":188,"y":395},{"x":238,"y":395},{"x":238,"y":445},{"x":188,"y":445}]},"landmarks":[{"type":"LEFT_EYE","position":{"x":200.46098,"y":415.97534,"z":-0.00038233522}},{"type":"RIGHT_EYE","position":{"x":217.64716,"y":407.4657,"z":-1.5979624}},{"type":"LEFT_OF_LEFT_EYEBROW","position":{"x":191.97968,"y":414.43237,"z":1.9923174}},{"type":"RIGHT_OF_LEFT_EYEBROW","position":{"x":202.75319,"y":410.16809,"z":-4.7933111}},{"type":"LEFT_OF_RIGHT_EYEBROW","position":{"x":211.69,"y":406.38452,"z":-5.5674911}},{"type":"RIGHT_OF_RIGHT_EYEBROW","position":{"x":223.48068,"y":401.09854,"z":-0.57531363}},{"type":"MIDPOINT_BETWEEN_EYES","position":{"x":208.91183,"y":411.60974,"z":-5.1120644}},{"type":"NOSE_TIP","position":{"x":213.75955,"y":423.79492,"z":-9.9139309}},{"type":"UPPER_LIP","position":{"x":216.78973,"y":429.53998,"z":-4.4318042}},{"type":"LOWER_LIP","position":{"x":219.79994,"y":435.77515,"z":-2.2548056}},{"type":"MOUTH_LEFT","position":{"x":210.52554,"y":434.72247,"z":2.045444}},{"type":"MOUTH_RIGHT","position":{"x":225.48784,"y":428.43289,"z":0.65253246}},{"type":"MOUTH_CENTER","position":{"x":218.24913,"y":432.30774,"z":-2.5877891}},{"type":"NOSE_BOTTOM_RIGHT","position":{"x":219.32861,"y":421.94699,"z":-2.4406357}},{"type":"NOSE_BOTTOM_LEFT","position":{"x":209.65569,"y":426.20865,"z":-1.5296445}},{"type":"NOSE_BOTTOM_CENTER","position":{"x":215.6537,"y":425.93677,"z":-4.8843226}},{"type":"LEFT_EYE_TOP_BOUNDARY","position":{"x":199.48264,"y":415.11035,"z":-1.4439765}},{"type":"LEFT_EYE_RIGHT_CORNER","position":{"x":204.46895,"y":414.87375,"z":-0.20436069}},{"type":"LEFT_EYE_BOTTOM_BOUNDARY","position":{"x":200.85997,"y":417.65106,"z":0.016331211}},{"type":"LEFT_EYE_LEFT_CORNER","position":{"x":196.51767,"y":417.70309,"z":2.2302275}},{"type":"LEFT_EYE_PUPIL","position":{"x":199.81047,"y":416.44193,"z":-0.4170824}},{"type":"RIGHT_EYE_TOP_BOUNDARY","position":{"x":218.0174,"y":406.84717,"z":-3.0609801}},{"type":"RIGHT_EYE_RIGHT_CORNER","position":{"x":222.44182,"y":406.10898,"z":-0.033950128}},{"type":"RIGHT_EYE_BOTTOM_BOUNDARY","position":{"x":218.61562,"y":408.92328,"z":-1.6490515}},{"type":"RIGHT_EYE_LEFT_CORNER","position":{"x":214.61102,"y":409.57211,"z":-1.1797646}},{"type":"RIGHT_EYE_PUPIL","position":{"x":218.83311,"y":407.94711,"z":-2.0995553}},{"type":"LEFT_EYEBROW_UPPER_MIDPOINT","position":{"x":196.24142,"y":410.25601,"z":-2.9690354}},{"type":"RIGHT_EYEBROW_UPPER_MIDPOINT","position":{"x":216.38759,"y":401.32162,"z":-4.730876}},{"type":"LEFT_EAR_TRAGION","position":{"x":193.28752,"y":427.57413,"z":26.976851}},{"type":"RIGHT_EAR_TRAGION","position":{"x":235.4303,"y":408.80438,"z":23.308439}},{"type":"FOREHEAD_GLABELLA","position":{"x":207.13664,"y":408.04453,"z":-5.9680209}},{"type":"CHIN_GNATHION","position":{"x":223.668,"y":443.74609,"z":1.4845077}},{"type":"CHIN_LEFT_GONION","position":{"x":200.41238,"y":439.53378,"z":19.823559}},{"type":"CHIN_RIGHT_GONION","position":{"x":238.51874,"y":422.56729,"z":16.496286}}],"rollAngle":-24.415377,"panAngle":-4.5772305,"tiltAngle":-5.4757223,"detectionConfidence":0.50981104,"landmarkingConfidence":0.56576085,"joyLikelihood":"VERY_UNLIKELY","sorrowLikelihood":"VERY_UNLIKELY","angerLikelihood":"VERY_UNLIKELY","surpriseLikelihood":"VERY_UNLIKELY","underExposedLikelihood":"VERY_UNLIKELY","blurredLikelihood":"VERY_UNLIKELY","headwearLikelihood":"VERY_UNLIKELY"},{"boundingPoly":{"vertices":[{"x":460,"y":346},{"x":528,"y":346},{"x":528,"y":425},{"x":460,"y":425}]},"fdBoundingPoly":{"vertices":[{"x":471,"y":368},{"x":521,"y":368},{"x":521,"y":418},{"x":471,"y":418}]},"landmarks":[{"type":"LEFT_EYE","position":{"x":481.09045,"y":389.67563,"z":-0.00013355468}},{"type":"RIGHT_EYE","position":{"x":496.62405,"y":380.61847,"z":-1.6084918}},{"type":"LEFT_OF_LEFT_EYEBROW","position":{"x":471.86847,"y":389.7341,"z":2.1985841}},{"type":"RIGHT_OF_LEFT_EYEBROW","position":{"x":482.3046,"y":384.15665,"z":-4.8000336}},{"type":"LEFT_OF_RIGHT_EYEBROW","position":{"x":490.98083,"y":379.46246,"z":-5.6436653}},{"type":"RIGHT_OF_RIGHT_EYEBROW","position":{"x":501.92743,"y":373.08853,"z":-0.86257339}},{"type":"MIDPOINT_BETWEEN_EYES","position":{"x":488.72144,"y":384.79126,"z":-5.1977587}},{"type":"NOSE_TIP","position":{"x":495.05475,"y":396.46231,"z":-10.207337}},{"type":"UPPER_LIP","position":{"x":498.82242,"y":402.33698,"z":-4.6462045}},{"type":"LOWER_LIP","position":{"x":502.55524,"y":408.39362,"z":-2.4729571}},{"type":"MOUTH_LEFT","position":{"x":493.48184,"y":408.38821,"z":1.8789742}},{"type":"MOUTH_RIGHT","position":{"x":507.39651,"y":400.39737,"z":0.42888558}},{"type":"MOUTH_CENTER","position":{"x":500.57214,"y":404.93121,"z":-2.7868702}},{"type":"NOSE_BOTTOM_RIGHT","position":{"x":500.54016,"y":394.4187,"z":-2.6240444}},{"type":"NOSE_BOTTOM_LEFT","position":{"x":491.84869,"y":399.62289,"z":-1.7696717}},{"type":"NOSE_BOTTOM_CENTER","position":{"x":497.26675,"y":398.50555,"z":-5.0914221}},{"type":"LEFT_EYE_TOP_BOUNDARY","position":{"x":479.5481,"y":389.56165,"z":-1.353596}},{"type":"LEFT_EYE_RIGHT_CORNER","position":{"x":484.7066,"y":388.42545,"z":-0.17856294}},{"type":"LEFT_EYE_BOTTOM_BOUNDARY","position":{"x":481.33359,"y":391.3652,"z":0.053096049}},{"type":"LEFT_EYE_LEFT_CORNER","position":{"x":476.86719,"y":392.53592,"z":2.387439}},{"type":"LEFT_EYE_PUPIL","position":{"x":480.02637,"y":390.88168,"z":-0.28745705}},{"type":"RIGHT_EYE_TOP_BOUNDARY","position":{"x":497.47269,"y":379.10742,"z":-3.1437058}},{"type":"RIGHT_EYE_RIGHT_CORNER","position":{"x":501.71109,"y":378.10535,"z":-0.15377241}},{"type":"RIGHT_EYE_BOTTOM_BOUNDARY","position":{"x":497.95639,"y":381.79968,"z":-1.7184374}},{"type":"RIGHT_EYE_LEFT_CORNER","position":{"x":494.18027,"y":382.58499,"z":-1.2117248}},{"type":"RIGHT_EYE_PUPIL","position":{"x":498.44861,"y":380.14972,"z":-2.145556}},{"type":"LEFT_EYEBROW_UPPER_MIDPOINT","position":{"x":475.6853,"y":384.99185,"z":-2.8429823}},{"type":"RIGHT_EYEBROW_UPPER_MIDPOINT","position":{"x":495.18756,"y":373.65082,"z":-4.7979698}},{"type":"LEFT_EAR_TRAGION","position":{"x":474.93335,"y":403.09598,"z":27.701788}},{"type":"RIGHT_EAR_TRAGION","position":{"x":515.70563,"y":379.2804,"z":23.656639}},{"type":"FOREHEAD_GLABELLA","position":{"x":486.51648,"y":381.50464,"z":-6.0126767}},{"type":"CHIN_GNATHION","position":{"x":507.42291,"y":416.1127,"z":1.3294444}},{"type":"CHIN_LEFT_GONION","position":{"x":483.43353,"y":414.49268,"z":20.23666}},{"type":"CHIN_RIGHT_GONION","position":{"x":520.34149,"y":392.94684,"z":16.562738}}],"rollAngle":-30.694757,"panAngle":-4.9330502,"tiltAngle":-4.9921012,"detectionConfidence":0.51038361,"landmarkingConfidence":0.52314699,"joyLikelihood":"VERY_UNLIKELY","sorrowLikelihood":"VERY_UNLIKELY","angerLikelihood":"VERY_UNLIKELY","surpriseLikelihood":"VERY_UNLIKELY","underExposedLikelihood":"VERY_UNLIKELY","blurredLikelihood":"VERY_UNLIKELY","headwearLikelihood":"VERY_UNLIKELY"},{"boundingPoly":{"vertices":[{"x":201,"y":222},{"x":261,"y":222},{"x":261,"y":292},{"x":201,"y":292}]},"fdBoundingPoly":{"vertices":[{"x":206,"y":240},{"x":256,"y":240},{"x":256,"y":290},{"x":206,"y":290}]},"landmarks":[{"type":"LEFT_EYE","position":{"x":218.60378,"y":260.19925,"z":-0.00039248052}},{"type":"RIGHT_EYE","position":{"x":234.18358,"y":252.42899,"z":-1.5957909}},{"type":"LEFT_OF_LEFT_EYEBROW","position":{"x":211.5125,"y":259.1189,"z":1.861004}},{"type":"RIGHT_OF_LEFT_EYEBROW","position":{"x":220.94519,"y":255.09854,"z":-4.2717023}},{"type":"LEFT_OF_RIGHT_EYEBROW","position":{"x":228.755,"y":251.61432,"z":-5.0391459}},{"type":"RIGHT_OF_RIGHT_EYEBROW","position":{"x":239.24576,"y":246.68973,"z":-0.70184195}},{"type":"MIDPOINT_BETWEEN_EYES","position":{"x":226.24103,"y":256.14822,"z":-4.6548524}},{"type":"NOSE_TIP","position":{"x":230.9491,"y":266.67365,"z":-9.0002584}},{"type":"UPPER_LIP","position":{"x":233.84138,"y":271.92749,"z":-4.2049427}},{"type":"LOWER_LIP","position":{"x":236.64755,"y":277.41479,"z":-2.3351552}},{"type":"MOUTH_LEFT","position":{"x":228.60822,"y":276.66379,"z":1.5496528}},{"type":"MOUTH_RIGHT","position":{"x":241.78435,"y":270.55896,"z":0.279733}},{"type":"MOUTH_CENTER","position":{"x":235.1833,"y":274.362,"z":-2.6001487}},{"type":"NOSE_BOTTOM_RIGHT","position":{"x":236.14703,"y":265.04117,"z":-2.3896842}},{"type":"NOSE_BOTTOM_LEFT","position":{"x":227.52969,"y":269.15714,"z":-1.5388436}},{"type":"NOSE_BOTTOM_CENTER","position":{"x":232.69405,"y":268.79749,"z":-4.5731149}},{"type":"LEFT_EYE_TOP_BOUNDARY","position":{"x":218.1411,"y":259.52118,"z":-1.2878418}},{"type":"LEFT_EYE_RIGHT_CORNER","position":{"x":222.30708,"y":259.16104,"z":-0.2277277}},{"type":"LEFT_EYE_BOTTOM_BOUNDARY","position":{"x":219.1721,"y":261.54459,"z":-0.02356948}},{"type":"LEFT_EYE_LEFT_CORNER","position":{"x":215.60333,"y":261.90292,"z":1.9994974}},{"type":"LEFT_EYE_PUPIL","position":{"x":218.47977,"y":260.69067,"z":-0.3883974}},{"type":"RIGHT_EYE_TOP_BOUNDARY","position":{"x":234.39488,"y":251.75702,"z":-2.9032116}},{"type":"RIGHT_EYE_RIGHT_CORNER","position":{"x":238.36116,"y":251.02866,"z":-0.25395158}},{"type":"RIGHT_EYE_BOTTOM_BOUNDARY","position":{"x":235.10176,"y":253.64731,"z":-1.6612521}},{"type":"RIGHT_EYE_LEFT_CORNER","position":{"x":231.55992,"y":254.41727,"z":-1.1954165}},{"type":"RIGHT_EYE_PUPIL","position":{"x":235.16216,"y":252.72102,"z":-2.0659273}},{"type":"LEFT_EYEBROW_UPPER_MIDPOINT","position":{"x":215.15894,"y":255.29306,"z":-2.5848603}},{"type":"RIGHT_EYEBROW_UPPER_MIDPOINT","position":{"x":232.81474,"y":246.89281,"z":-4.3389416}},{"type":"LEFT_EAR_TRAGION","position":{"x":213.27266,"y":270.86438,"z":23.982853}},{"type":"RIGHT_EAR_TRAGION","position":{"x":250.22261,"y":253.22273,"z":20.313515}},{"type":"FOREHEAD_GLABELLA","position":{"x":224.7379,"y":253.06624,"z":-5.3643327}},{"type":"CHIN_GNATHION","position":{"x":240.32567,"y":284.42175,"z":0.89818311}},{"type":"CHIN_LEFT_GONION","position":{"x":219.78539,"y":281.26947,"z":17.488258}},{"type":"CHIN_RIGHT_GONION","position":{"x":253.19348,"y":265.33044,"z":14.171227}}],"rollAngle":-25.951361,"panAngle":-5.1364264,"tiltAngle":-4.9046168,"detectionConfidence":0.50501066,"landmarkingConfidence":0.50656581,"joyLikelihood":"VERY_UNLIKELY","sorrowLikelihood":"VERY_UNLIKELY","angerLikelihood":"VERY_UNLIKELY","surpriseLikelihood":"VERY_UNLIKELY","underExposedLikelihood":"VERY_UNLIKELY","blurredLikelihood":"VERY_UNLIKELY","headwearLikelihood":"VERY_UNLIKELY"},{"boundingPoly":{"vertices":[{"x":72,"y":229},{"x":133,"y":229},{"x":133,"y":300},{"x":72,"y":300}]},"fdBoundingPoly":{"vertices":[{"x":76,"y":248},{"x":126,"y":248},{"x":126,"y":298},{"x":76,"y":298}]},"landmarks":[{"type":"LEFT_EYE","position":{"x":89.361504,"y":268.42035,"z":-0.0002658029}},{"type":"RIGHT_EYE","position":{"x":105.69749,"y":261.09106,"z":-2.2759345}},{"type":"LEFT_OF_LEFT_EYEBROW","position":{"x":82.259689,"y":266.93655,"z":2.0409214}},{"type":"RIGHT_OF_LEFT_EYEBROW","position":{"x":91.862534,"y":263.26602,"z":-4.6131501}},{"type":"LEFT_OF_RIGHT_EYEBROW","position":{"x":99.997429,"y":260.00665,"z":-5.708333}},{"type":"RIGHT_OF_RIGHT_EYEBROW","position":{"x":111.09307,"y":255.24315,"z":-1.6399703}},{"type":"MIDPOINT_BETWEEN_EYES","position":{"x":97.337189,"y":264.66916,"z":-5.081111}},{"type":"NOSE_TIP","position":{"x":101.62846,"y":275.57111,"z":-9.303093}},{"type":"UPPER_LIP","position":{"x":104.51214,"y":280.99362,"z":-4.3105502}},{"type":"LOWER_LIP","position":{"x":107.22168,"y":286.59238,"z":-2.2969303}},{"type":"MOUTH_LEFT","position":{"x":99.212547,"y":285.51172,"z":1.8317003}},{"type":"MOUTH_RIGHT","position":{"x":112.71854,"y":279.77466,"z":0.024700787}},{"type":"MOUTH_CENTER","position":{"x":105.8872,"y":283.39343,"z":-2.6275861}},{"type":"NOSE_BOTTOM_RIGHT","position":{"x":107.09026,"y":273.96817,"z":-2.7469442}},{"type":"NOSE_BOTTOM_LEFT","position":{"x":97.951645,"y":277.69562,"z":-1.4858094}},{"type":"NOSE_BOTTOM_CENTER","position":{"x":103.36909,"y":277.59369,"z":-4.761662}},{"type":"LEFT_EYE_TOP_BOUNDARY","position":{"x":88.960297,"y":267.64499,"z":-1.3495896}},{"type":"LEFT_EYE_RIGHT_CORNER","position":{"x":93.18338,"y":267.39804,"z":-0.37129593}},{"type":"LEFT_EYE_BOTTOM_BOUNDARY","position":{"x":89.820358,"y":269.69797,"z":-0.011968231}},{"type":"LEFT_EYE_LEFT_CORNER","position":{"x":86.362671,"y":269.8844,"z":2.1525838}},{"type":"LEFT_EYE_PUPIL","position":{"x":89.282738,"y":268.81473,"z":-0.4022966}},{"type":"RIGHT_EYE_TOP_BOUNDARY","position":{"x":105.80814,"y":260.34341,"z":-3.6478736}},{"type":"RIGHT_EYE_RIGHT_CORNER","position":{"x":110.01096,"y":259.69797,"z":-1.045131}},{"type":"RIGHT_EYE_BOTTOM_BOUNDARY","position":{"x":106.61112,"y":262.366,"z":-2.3280454}},{"type":"RIGHT_EYE_LEFT_CORNER","position":{"x":102.9372,"y":262.86252,"z":-1.7480538}},{"type":"RIGHT_EYE_PUPIL","position":{"x":106.57313,"y":261.32867,"z":-2.7823834}},{"type":"LEFT_EYEBROW_UPPER_MIDPOINT","position":{"x":86.025566,"y":263.24579,"z":-2.7391801}},{"type":"RIGHT_EYEBROW_UPPER_MIDPOINT","position":{"x":104.32079,"y":255.34732,"z":-5.2348132}},{"type":"LEFT_EAR_TRAGION","position":{"x":84.235367,"y":278.25055,"z":24.960604}},{"type":"RIGHT_EAR_TRAGION","position":{"x":122.51446,"y":261.63895,"z":19.756376}},{"type":"FOREHEAD_GLABELLA","position":{"x":95.823112,"y":261.39923,"z":-5.8853111}},{"type":"CHIN_GNATHION","position":{"x":110.80872,"y":293.78192,"z":1.1413447}},{"type":"CHIN_LEFT_GONION","position":{"x":90.353508,"y":289.31332,"z":18.510891}},{"type":"CHIN_RIGHT_GONION","position":{"x":124.9639,"y":274.31885,"z":13.793832}}],"rollAngle":-24.16502,"panAngle":-7.161788,"tiltAngle":-5.9325271,"detectionConfidence":0.51307619,"landmarkingConfidence":0.49467307,"joyLikelihood":"VERY_UNLIKELY","sorrowLikelihood":"VERY_UNLIKELY","angerLikelihood":"VERY_UNLIKELY","surpriseLikelihood":"VERY_UNLIKELY","underExposedLikelihood":"VERY_UNLIKELY","blurredLikelihood":"VERY_UNLIKELY","headwearLikelihood":"VERY_UNLIKELY"},{"boundingPoly":{"vertices":[{"x":40,"y":380},{"x":109,"y":380},{"x":109,"y":459},{"x":40,"y":459}]},"fdBoundingPoly":{"vertices":[{"x":48,"y":403},{"x":98,"y":403},{"x":98,"y":453},{"x":48,"y":453}]},"landmarks":[{"type":"LEFT_EYE","position":{"x":60.459373,"y":423.41656,"z":-0.00042589448}},{"type":"RIGHT_EYE","position":{"x":78.711838,"y":415.16635,"z":-2.3697011}},{"type":"LEFT_OF_LEFT_EYEBROW","position":{"x":52.322701,"y":421.80487,"z":2.2635822}},{"type":"RIGHT_OF_LEFT_EYEBROW","position":{"x":63.031662,"y":417.64417,"z":-5.0516186}},{"type":"LEFT_OF_RIGHT_EYEBROW","position":{"x":72.162628,"y":413.7955,"z":-6.2008233}},{"type":"RIGHT_OF_RIGHT_EYEBROW","position":{"x":84.582726,"y":408.68002,"z":-1.4961528}},{"type":"MIDPOINT_BETWEEN_EYES","position":{"x":69.072601,"y":419.14468,"z":-5.5669456}},{"type":"NOSE_TIP","position":{"x":73.453598,"y":431.73453,"z":-10.386794}},{"type":"UPPER_LIP","position":{"x":77.043877,"y":437.41913,"z":-4.8409534}},{"type":"LOWER_LIP","position":{"x":80.06543,"y":443.65762,"z":-2.6502094}},{"type":"MOUTH_LEFT","position":{"x":70.876312,"y":442.44568,"z":1.9843777}},{"type":"MOUTH_RIGHT","position":{"x":86.019211,"y":436.24017,"z":-0.00047117448}},{"type":"MOUTH_CENTER","position":{"x":78.833191,"y":439.89154,"z":-2.990252}},{"type":"NOSE_BOTTOM_RIGHT","position":{"x":79.611282,"y":429.72708,"z":-3.0525429}},{"type":"NOSE_BOTTOM_LEFT","position":{"x":69.889778,"y":434.29678,"z":-1.6384087}},{"type":"NOSE_BOTTOM_CENTER","position":{"x":75.611298,"y":433.88559,"z":-5.3067737}},{"type":"LEFT_EYE_TOP_BOUNDARY","position":{"x":59.782921,"y":422.5412,"z":-1.4810474}},{"type":"LEFT_EYE_RIGHT_CORNER","position":{"x":64.479263,"y":422.20285,"z":-0.36876342}},{"type":"LEFT_EYE_BOTTOM_BOUNDARY","position":{"x":60.979172,"y":424.85294,"z":-0.01620261}},{"type":"LEFT_EYE_LEFT_CORNER","position":{"x":56.873043,"y":425.06537,"z":2.3794305}},{"type":"LEFT_EYE_PUPIL","position":{"x":60.132004,"y":423.85657,"z":-0.43786898}},{"type":"RIGHT_EYE_TOP_BOUNDARY","position":{"x":78.578232,"y":414.42984,"z":-3.8655629}},{"type":"RIGHT_EYE_RIGHT_CORNER","position":{"x":83.157761,"y":413.71548,"z":-0.95498747}},{"type":"RIGHT_EYE_BOTTOM_BOUNDARY","position":{"x":79.614716,"y":416.45386,"z":-2.4188447}},{"type":"RIGHT_EYE_LEFT_CORNER","position":{"x":75.448257,"y":417.22525,"z":-1.7922269}},{"type":"RIGHT_EYE_PUPIL","position":{"x":79.417114,"y":415.53156,"z":-2.90783}},{"type":"LEFT_EYEBROW_UPPER_MIDPOINT","position":{"x":56.510994,"y":417.62546,"z":-3.0021429}},{"type":"RIGHT_EYEBROW_UPPER_MIDPOINT","position":{"x":76.92482,"y":408.84589,"z":-5.5894709}},{"type":"LEFT_EAR_TRAGION","position":{"x":54.316841,"y":434.62332,"z":27.679098}},{"type":"RIGHT_EAR_TRAGION","position":{"x":97.016739,"y":416.19656,"z":22.255833}},{"type":"FOREHEAD_GLABELLA","position":{"x":67.439926,"y":415.55963,"z":-6.4283786}},{"type":"CHIN_GNATHION","position":{"x":84.004036,"y":451.72107,"z":1.1188716}},{"type":"CHIN_LEFT_GONION","position":{"x":61.151974,"y":446.89743,"z":20.39551}},{"type":"CHIN_RIGHT_GONION","position":{"x":99.750137,"y":430.24637,"z":15.500597}}],"rollAngle":-23.977322,"panAngle":-6.6686416,"tiltAngle":-5.5262895,"detectionConfidence":0.51758558,"landmarkingConfidence":0.52053845,"joyLikelihood":"VERY_UNLIKELY","sorrowLikelihood":"VERY_UNLIKELY","angerLikelihood":"VERY_UNLIKELY","surpriseLikelihood":"VERY_UNLIKELY","underExposedLikelihood":"VERY_UNLIKELY","blurredLikelihood":"VERY_UNLIKELY","headwearLikelihood":"VERY_UNLIKELY"}],"labelAnnotations":[{"mid":"/m/0gjbg72","description":"Shelf","score":0.92306226,"topicality":0.92306226},{"mid":"/m/025dyy","description":"Box","score":0.79123956,"topicality":0.79123956},{"mid":"/m/0h8n982","description":"Shelving","score":0.75082874,"topicality":0.75082874},{"mid":"/m/08_4sd","description":"Collection","score":0.74880552,"topicality":0.74880552},{"mid":"/m/0c_jw","description":"Furniture","score":0.68205041,"topicality":0.68205041}]}]}
