{"responses":[{"labelAnnotations":[{"mid":"/m/01k74n","description":"Facial expression","score":0.94438577,"topicality":0.94438577},{"mid":"/m/0215n","description":"Cartoon","score":0.8874557,"topicality":0.8874557},{"mid":"/m/01kr8f","description":"Illustration","score":0.80692184,"topicality":0.80692184},{"mid":"/m/0jjw","description":"Art","score":0.62534767,"topicality":0.62534767},{"mid":"/m/0jxy","description":"Anime","score":0.61882377,"topicality":0.61882377},{"mid":"/m/02csf","description":"Drawing","score":0.53659421,"topicality":0.53659421},{"mid":"/m/02h7lkt","description":"Fictional character","score":0.52791756,"topicality":0.52791756},{"mid":"/m/012yh1","description":"Style","score":0.50951844,"topicality":0.50951844}]}]}
