{"responses":[{"labelAnnotations":[{"mid":"/m/01fklc","description":"Pink","score":0.95513105,"topicality":0.95513105},{"mid":"/m/0404d","description":"Jewellery","score":0.93862659,"topicality":0.93862659},{"mid":"/m/01llwg","description":"Necklace","score":0.92057461,"topicality":0.92057461},{"mid":"/m/0463sg","description":"Fashion accessory","score":0.87803841,"topicality":0.87803841},{"mid":"/m/01krjr","description":"Pendant","score":0.8504709,"topicality":0.8504709},{"mid":"/m/0b5gs","description":"Branch","score":0.84331679,"topicality":0.84331679},{"mid":"/m/0h8kxbv","description":"Body jewelry","score":0.81356806,"topicality":0.81356806},{"mid":"/m/09t49","description":"Leaf","score":0.75946116,"topicality":0.75946116},{"mid":"/m/04t7l","description":"Metal","score":0.7537728,"topicality":0.7537728},{"mid":"/m/0269r2s","description":"Chain","score":0.75103277,"topicality":0.75103277}]}]}
