{"responses":[{"logoAnnotations":[{"description":"sleeping with sirens","score":0.83182502,"boundingPoly":{"vertices":[{"x":366,"y":5},{"x":683,"y":5},{"x":683,"y":125},{"x":366,"y":125}]}}],"labelAnnotations":[{"mid":"/m/07s6nbt","description":"Text","score":0.91213948,"topicality":0.91213948},{"mid":"/m/03gq5hm","description":"Font","score":0.80401665,"topicality":0.80401665},{"mid":"/m/03scnj","description":"Line","score":0.75476062,"topicality":0.75476062}],"safeSearchAnnotation":{"adult":"VERY_UNLIKELY","spoof":"VERY_UNLIKELY","medical":"VERY_UNLIKELY","violence":"VERY_UNLIKELY","racy":"VERY_UNLIKELY"}}]}
