{"responses":[{"landmarkAnnotations":[{"mid":"/m/068trq","description":"Minnewaska State Park Preserve","score":0.20084032,"boundingPoly":{"vertices":[{"x":461,"y":67},{"x":509,"y":67},{"x":509,"y":337},{"x":461,"y":337}]},"locations":[{"latLng":{"latitude":41.734349000000002,"longitude":-74.236874999999998}}]}],"logoAnnotations":[{"mid":"/m/09ck55","description":"i love ny","score":0.92330003,"boundingPoly":{"vertices":[{"x":530,"y":532},{"x":619,"y":532},{"x":619,"y":622},{"x":530,"y":622}]}}],"labelAnnotations":[{"mid":"/m/03ktm1","description":"Body of water","score":0.98206145,"topicality":0.98206145},{"mid":"/m/0j2kx","description":"Waterfall","score":0.98142916,"topicality":0.98142916},{"mid":"/m/0838f","description":"Water","score":0.97168678,"topicality":0.97168678},{"mid":"/m/015s2f","description":"Water resources","score":0.96833163,"topicality":0.96833163},{"mid":"/m/05h0n","description":"Nature","score":0.96639413,"topicality":0.96639413},{"mid":"/m/03d28y3","description":"Natural landscape","score":0.93981558,"topicality":0.93981558},{"mid":"/m/0swq_","description":"Nature reserve","score":0.92763638,"topicality":0.92763638},{"mid":"/m/03kj4q","description":"Watercourse","score":0.91112936,"topicality":0.91112936},{"mid":"/m/07j7r","description":"Tree","score":0.83482164,"topicality":0.83482164},{"mid":"/m/090j23","description":"Water feature","score":0.82224482,"topicality":0.82224482}]}]}
