{"responses":[{"labelAnnotations":[{"mid":"/m/0j2kx","description":"Waterfall","score":0.98501384,"topicality":0.98501384},{"mid":"/m/03ktm1","description":"Body of water","score":0.97761822,"topicality":0.97761822},{"mid":"/m/0838f","description":"Water","score":0.97270185,"topicality":0.97270185},{"mid":"/m/05h0n","description":"Nature","score":0.95502943,"topicality":0.95502943},{"mid":"/m/03kj4q","description":"Watercourse","score":0.90641093,"topicality":0.90641093},{"mid":"/m/015s2f","description":"Water resources","score":0.90516615,"topicality":0.90516615},{"mid":"/m/03d28y3","description":"Natural landscape","score":0.88551891,"topicality":0.88551891},{"mid":"/m/090j23","description":"Water feature","score":0.77338713,"topicality":0.77338713},{"mid":"/m/01cbzq","description":"Rock","score":0.7591666,"topicality":0.7591666},{"mid":"/m/021krv","description":"State park","score":0.68528998,"topicality":0.68528998}]}]}
