{"responses":[{"landmarkAnnotations":[{"mid":"/m/0cv4c","description":"Brooklyn Bridge","score":0.44580323,"boundingPoly":{"vertices":[{"x":57,"y":150},{"x":617,"y":150},{"x":617,"y":244},{"x":57,"y":244}]},"locations":[{"latLng":{"latitude":40.705725999999999,"longitude":-73.996953000000005}}]},{"mid":"/m/02nd_","description":"New York City","score":0.24018374,"boundingPoly":{"vertices":[{"x":46,"y":161},{"x":116,"y":161},{"x":116,"y":228},{"x":46,"y":228}]},"locations":[{"latLng":{"latitude":40.748432999999999,"longitude":-73.985753000000003}}]}],"labelAnnotations":[{"mid":"/m/034z7h","description":"Cityscape","score":0.98467594,"topicality":0.98467594},{"mid":"/m/01n32","description":"City","score":0.98125535,"topicality":0.98125535},{"mid":"/m/01bqvp","description":"Sky","score":0.97617966,"topicality":0.97617966},{"mid":"/m/0204fg","description":"Skyline","score":0.96576351,"topicality":0.96576351},{"mid":"/m/0j_s4","description":"Metropolitan area","score":0.9487865,"topicality":0.9487865},{"mid":"/m/056mk","description":"Metropolis","score":0.92948717,"topicality":0.92948717},{"mid":"/m/0fpdgl","description":"Human settlement","score":0.92610711,"topicality":0.92610711},{"mid":"/m/039jbq","description":"Urban area","score":0.91864175,"topicality":0.91864175},{"mid":"/m/079cl","description":"Skyscraper","score":0.90551096,"topicality":0.90551096},{"mid":"/m/02q7ylj","description":"Daytime","score":0.90233541,"topicality":0.90233541}]}]}
