{"responses":[{"labelAnnotations":[{"mid":"/m/01prls","description":"Land vehicle","score":0.99616271,"topicality":0.99616271},{"mid":"/m/07yv9","description":"Vehicle","score":0.99030316,"topicality":0.99030316},{"mid":"/m/0k4j","description":"Car","score":0.98701257,"topicality":0.98701257},{"mid":"/m/012f08","description":"Motor vehicle","score":0.97437727,"topicality":0.97437727},{"mid":"/m/0cvq3","description":"Pickup truck","score":0.95885181,"topicality":0.95885181},{"mid":"/m/07r04","description":"Truck","score":0.85124314,"topicality":0.85124314},{"mid":"/m/01xsb3","description":"Classic car","score":0.82637888,"topicality":0.82637888},{"mid":"/g/12233hjw","description":"Classic","score":0.56664348,"topicality":0.56664348},{"mid":"/m/03m7v4","description":"Hardtop","score":0.54563534,"topicality":0.54563534},{"mid":"/m/01xq49","description":"Vintage car","score":0.50609082,"topicality":0.50609082}]}]}
