{"responses":[{"labelAnnotations":[{"mid":"/m/05h0n","description":"Nature","score":0.95761263,"topicality":0.95761263},{"mid":"/m/03k5cs","description":"Formation","score":0.95399517,"topicality":0.95399517},{"mid":"/m/01r8w","description":"Cave","score":0.94097227,"topicality":0.94097227},{"mid":"/m/02p1_8d","description":"Narrows","score":0.74706662,"topicality":0.74706662},{"mid":"/m/036hv","description":"Geology","score":0.74524796,"topicality":0.74524796},{"mid":"/m/01r8g","description":"Caving","score":0.72283608,"topicality":0.72283608},{"mid":"/m/01cbzq","description":"Rock","score":0.69812059,"topicality":0.69812059},{"mid":"/m/07j7r","description":"Tree","score":0.68692183,"topicality":0.68692183},{"mid":"/m/02c9_23","description":"Coastal and oceanic landforms","score":0.62874323,"topicality":0.62874323},{"mid":"/m/07sn5gn","description":"Geological phenomenon","score":0.61630917,"topicality":0.61630917}]}]}
