{"responses":[{"labelAnnotations":[{"mid":"/m/03qtwd","description":"Crowd","score":0.9564082,"topicality":0.9564082},{"mid":"/m/01bqvp","description":"Sky","score":0.95082861,"topicality":0.95082861},{"mid":"/m/09g5pq","description":"People","score":0.93127215,"topicality":0.93127215},{"mid":"/m/02q7ylj","description":"Daytime","score":0.86343998,"topicality":0.86343998},{"mid":"/m/03nfmq","description":"Architecture","score":0.76329434,"topicality":0.76329434},{"mid":"/m/07j7r","description":"Tree","score":0.74697447,"topicality":0.74697447},{"mid":"/m/0csby","description":"Cloud","score":0.74275196,"topicality":0.74275196},{"mid":"/m/078qz","description":"Summer","score":0.72799528,"topicality":0.72799528},{"mid":"/m/080kstp","description":"Flip (acrobatic)","score":0.71175045,"topicality":0.71175045},{"mid":"/m/07bxq","description":"Tourism","score":0.7109198,"topicality":0.7109198}]}]}
