{"responses":[{"labelAnnotations":[{"mid":"/m/0bmgjqz","description":"Sport venue","score":0.95816225,"topicality":0.95816225},{"mid":"/m/013x8v","description":"Fan","score":0.87672573,"topicality":0.87672573},{"mid":"/m/03qtwd","description":"Crowd","score":0.81996733,"topicality":0.81996733},{"mid":"/m/018lrm","description":"Arena","score":0.81773078,"topicality":0.81773078},{"mid":"/m/019cfy","description":"Stadium","score":0.77572322,"topicality":0.77572322},{"mid":"/m/03bt1gh","description":"Games","score":0.69032127,"topicality":0.69032127},{"mid":"/m/06ntj","description":"Sports","score":0.67410481,"topicality":0.67410481},{"mid":"/m/03x045","description":"Team sport","score":0.63589782,"topicality":0.63589782},{"mid":"/m/02_sx","description":"Floorball","score":0.59212959,"topicality":0.59212959},{"mid":"/m/02qg91d","description":"Field house","score":0.5771789,"topicality":0.5771789}]}]}
