{"responses":[{"labelAnnotations":[{"mid":"/m/015kr","description":"Bridge","score":0.96965104,"topicality":0.96965104},{"mid":"/m/03ms9p","description":"Truss bridge","score":0.93331283,"topicality":0.93331283},{"mid":"/m/07j7r","description":"Tree","score":0.9158687,"topicality":0.9158687},{"mid":"/m/025rw19","description":"Iron","score":0.88115227,"topicality":0.88115227},{"mid":"/m/0bm8qyq","description":"Thoroughfare","score":0.75871629,"topicality":0.75871629},{"mid":"/m/0csy8","description":"Suspension bridge","score":0.74070132,"topicality":0.74070132},{"mid":"/m/01txr2","description":"Spring","score":0.73575652,"topicality":0.73575652},{"mid":"/m/06gfj","description":"Road","score":0.72739369,"topicality":0.72739369},{"mid":"/m/0df8xq","description":"Nonbuilding structure","score":0.72675091,"topicality":0.72675091},{"mid":"/m/017kvv","description":"Infrastructure","score":0.71681386,"topicality":0.71681386}]}]}
