{"responses":[{"labelAnnotations":[{"mid":"/m/07j7r","description":"Tree","score":0.9815641,"topicality":0.9815641},{"mid":"/m/05h0n","description":"Nature","score":0.95161229,"topicality":0.95161229},{"mid":"/m/02py09","description":"Natural environment","score":0.93452102,"topicality":0.93452102},{"mid":"/m/02zr8","description":"Forest","score":0.93132544,"topicality":0.93132544},{"mid":"/m/0hm03","description":"Trail","score":0.91164309,"topicality":0.91164309},{"mid":"/m/0b5gs","description":"Branch","score":0.9073751,"topicality":0.9073751},{"mid":"/m/0hnc1","description":"Woodland","score":0.90124649,"topicality":0.90124649},{"mid":"/m/023bbt","description":"Wilderness","score":0.88903213,"topicality":0.88903213},{"mid":"/m/03d28y3","description":"Natural landscape","score":0.88551891,"topicality":0.88551891},{"mid":"/m/0swq_","description":"Nature reserve","score":0.87966442,"topicality":0.87966442}]}]}
