{"responses":[{"labelAnnotations":[{"mid":"/m/06_dn","description":"Snow","score":0.95794529,"topicality":0.95794529},{"mid":"/m/086mh","description":"Winter","score":0.95101881,"topicality":0.95101881},{"mid":"/m/01bqvp","description":"Sky","score":0.94539726,"topicality":0.94539726},{"mid":"/m/01c791","description":"Freezing","score":0.86963665,"topicality":0.86963665},{"mid":"/m/02_ktj","description":"Morning","score":0.80161548,"topicality":0.80161548},{"mid":"/m/03jm5","description":"House","score":0.79084152,"topicality":0.79084152},{"mid":"/m/01f4td","description":"Rural area","score":0.7735911,"topicality":0.7735911},{"mid":"/m/0vllx","description":"Barn","score":0.74478382,"topicality":0.74478382},{"mid":"/m/0csby","description":"Cloud","score":0.74275196,"topicality":0.74275196},{"mid":"/m/0cgh4","description":"Building","score":0.71529496,"topicality":0.71529496}]}]}
