{"responses":[{"labelAnnotations":[{"mid":"/m/02rfdq","description":"Interior design","score":0.88497669,"topicality":0.88497669},{"mid":"/m/06ht1","description":"Room","score":0.82639521,"topicality":0.82639521},{"mid":"/m/019sc6","description":"Lighting","score":0.81254381,"topicality":0.81254381},{"mid":"/m/0cgh4","description":"Building","score":0.75686806,"topicality":0.75686806},{"mid":"/m/02cwm","description":"Design","score":0.72032273,"topicality":0.72032273},{"mid":"/m/03nfmq","description":"Architecture","score":0.65451187,"topicality":0.65451187},{"mid":"/m/03jm5","description":"House","score":0.53693008,"topicality":0.53693008},{"mid":"/m/0c_jw","description":"Furniture","score":0.53317308,"topicality":0.53317308},{"mid":"/m/03gfsp","description":"Ceiling","score":0.50640857,"topicality":0.50640857}]}]}
