{"responses":[{"labelAnnotations":[{"mid":"/m/01bqvp","description":"Sky","score":0.98808515,"topicality":0.98808515},{"mid":"/m/05h0n","description":"Nature","score":0.94942278,"topicality":0.94942278},{"mid":"/m/0csby","description":"Cloud","score":0.94767946,"topicality":0.94767946},{"mid":"/m/01fnns","description":"Vegetation","score":0.94327015,"topicality":0.94327015},{"mid":"/m/023bbt","description":"Wilderness","score":0.93805021,"topicality":0.93805021},{"mid":"/g/11jxkqbpp","description":"Mountainous landforms","score":0.93203646,"topicality":0.93203646},{"mid":"/m/09d_r","description":"Mountain","score":0.92191869,"topicality":0.92191869},{"mid":"/m/02q7ylj","description":"Daytime","score":0.91319007,"topicality":0.91319007},{"mid":"/m/01n32","description":"City","score":0.89552277,"topicality":0.89552277},{"mid":"/m/07j7r","description":"Tree","score":0.88663232,"topicality":0.88663232}]}]}
