{"responses":[{"labelAnnotations":[{"mid":"/m/06ht1","description":"Room","score":0.74443161,"topicality":0.74443161},{"mid":"/m/0191f8","description":"Learning","score":0.73338771,"topicality":0.73338771},{"mid":"/m/0ytgt","description":"Child","score":0.72773254,"topicality":0.72773254},{"mid":"/m/04bcr3","description":"Table","score":0.71705842,"topicality":0.71705842},{"mid":"/m/01d30f","description":"Teacher","score":0.56727618,"topicality":0.56727618},{"mid":"/m/081rb","description":"Writing","score":0.55480701,"topicality":0.55480701},{"mid":"/m/01y9k5","description":"Desk","score":0.51027882,"topicality":0.51027882},{"mid":"/m/0f1tz","description":"Calligraphy","score":0.5083971,"topicality":0.5083971}],"textAnnotations":[{"locale":"en","description":"HIS VOICE\nIS THE\nWHISPER\nAFTER\nTHE NOISE\n","boundingPoly":{"vertices":[{"x":341,"y":111},{"x":513,"y":111},{"x":513,"y":338},{"x":341,"y":338}]}},{"description":"HIS","boundingPoly":{"vertices":[{"x":347,"y":111},{"x":391,"y":111},{"x":391,"y":137},{"x":347,"y":137}]}},{"description":"VOICE","boundingPoly":{"vertices":[{"x":417,"y":111},{"x":503,"y":112},{"x":503,"y":139},{"x":417,"y":138}]}},{"description":"IS","boundingPoly":{"vertices":[{"x":376,"y":166},{"x":400,"y":166},{"x":400,"y":192},{"x":376,"y":192}]}},{"description":"THE","boundingPoly":{"vertices":[{"x":418,"y":166},{"x":474,"y":167},{"x":474,"y":194},{"x":418,"y":193}]}},{"description":"WHISPER","boundingPoly":{"vertices":[{"x":348,"y":211},{"x":506,"y":211},{"x":506,"y":237},{"x":348,"y":237}]}},{"description":"AFTER","boundingPoly":{"vertices":[{"x":368,"y":255},{"x":488,"y":255},{"x":488,"y":281},{"x":368,"y":281}]}},{"description":"THE","boundingPoly":{"vertices":[{"x":341,"y":309},{"x":402,"y":309},{"x":402,"y":335},{"x":341,"y":335}]}},{"description":"NOISE","boundingPoly":{"vertices":[{"x":423,"y":304},{"x":513,"y":303},{"x":513,"y":337},{"x":423,"y":338}]}}],"fullTextAnnotation":{"pages":[{"property":{"detectedLanguages":[{"languageCode":"en","confidence":1}]},"width":1080,"height":1080,"blocks":[{"property":{"detectedLanguages":[{"languageCode":"en","confidence":1}]},"boundingBox":{"vertices":[{"x":347,"y":111},{"x":503,"y":112},{"x":503,"y":138},{"x":347,"y":137}]},"paragraphs":[{"property":{"detectedLanguages":[{"languageCode":"en","confidence":1}]},"boundingBox":{"vertices":[{"x":347,"y":111},{"x":503,"y":112},{"x":503,"y":138},{"x":347,"y":137}]},"words":[{"property":{"detectedLanguages":[{"languageCode":"en"}]},"boundingBox":{"vertices":[{"x":347,"y":111},{"x":391,"y":111},{"x":391,"y":137},{"x":347,"y":137}]},"symbols":[{"property":{"detectedLanguages":[{"languageCode":"en"}]},"boundingBox":{"vertices":[{"x":347,"y":111},{"x":362,"y":111},{"x":362,"y":137},{"x":347,"y":137}]},"text":"H"},{"property":{"detectedLanguages":[{"languageCode":"en"}]},"boundingBox":{"vertices":[{"x":369,"y":111},{"x":372,"y":111},{"x":372,"y":137},{"x":369,"y":137}]},"text":"I"},{"property":{"detectedLanguages":[{"languageCode":"en"}],"detectedBreak":{"type":"SPACE"}},"boundingBox":{"vertices":[{"x":376,"y":111},{"x":391,"y":111},{"x":391,"y":137},{"x":376,"y":137}]},"text":"S"}]},{"property":{"detectedLanguages":[{"languageCode":"en"}]},"boundingBox":{"vertices":[{"x":417,"y":111},{"x":503,"y":112},{"x":503,"y":139},{"x":417,"y":138}]},"symbols":[{"property":{"detectedLanguages":[{"languageCode":"en"}]},"boundingBox":{"vertices":[{"x":417,"y":112},{"x":433,"y":112},{"x":433,"y":138},{"x":417,"y":138}]},"text":"V"},{"property":{"detectedLanguages":[{"languageCode":"en"}]},"boundingBox":{"vertices":[{"x":436,"y":112},{"x":452,"y":112},{"x":452,"y":138},{"x":436,"y":138}]},"text":"O"},{"property":{"detectedLanguages":[{"languageCode":"en"}]},"boundingBox":{"vertices":[{"x":459,"y":112},{"x":462,"y":112},{"x":462,"y":138},{"x":459,"y":138}]},"text":"I"},{"property":{"detectedLanguages":[{"languageCode":"en"}]},"boundingBox":{"vertices":[{"x":467,"y":112},{"x":482,"y":112},{"x":482,"y":138},{"x":467,"y":138}]},"text":"C"},{"property":{"detectedLanguages":[{"languageCode":"en"}],"detectedBreak":{"type":"EOL_SURE_SPACE"}},"boundingBox":{"vertices":[{"x":489,"y":112},{"x":503,"y":112},{"x":503,"y":138},{"x":489,"y":138}]},"text":"E"}]}]}],"blockType":"TEXT"},{"property":{"detectedLanguages":[{"languageCode":"en","confidence":1}]},"boundingBox":{"vertices":[{"x":376,"y":166},{"x":474,"y":168},{"x":474,"y":194},{"x":376,"y":192}]},"paragraphs":[{"property":{"detectedLanguages":[{"languageCode":"en","confidence":1}]},"boundingBox":{"vertices":[{"x":376,"y":166},{"x":474,"y":168},{"x":474,"y":194},{"x":376,"y":192}]},"words":[{"property":{"detectedLanguages":[{"languageCode":"en"}]},"boundingBox":{"vertices":[{"x":376,"y":166},{"x":400,"y":166},{"x":400,"y":192},{"x":376,"y":192}]},"symbols":[{"property":{"detectedLanguages":[{"languageCode":"en"}]},"boundingBox":{"vertices":[{"x":376,"y":166},{"x":380,"y":166},{"x":380,"y":192},{"x":376,"y":192}]},"text":"I"},{"property":{"detectedLanguages":[{"languageCode":"en"}],"detectedBreak":{"type":"SPACE"}},"boundingBox":{"vertices":[{"x":385,"y":166},{"x":400,"y":166},{"x":400,"y":192},{"x":385,"y":192}]},"text":"S"}]},{"property":{"detectedLanguages":[{"languageCode":"en"}]},"boundingBox":{"vertices":[{"x":418,"y":166},{"x":474,"y":167},{"x":474,"y":194},{"x":418,"y":193}]},"symbols":[{"property":{"detectedLanguages":[{"languageCode":"en"}]},"boundingBox":{"vertices":[{"x":418,"y":167},{"x":434,"y":167},{"x":434,"y":193},{"x":418,"y":193}]},"text":"T"},{"property":{"detectedLanguages":[{"languageCode":"en"}]},"boundingBox":{"vertices":[{"x":439,"y":167},{"x":453,"y":167},{"x":453,"y":193},{"x":439,"y":193}]},"text":"H"},{"property":{"detectedLanguages":[{"languageCode":"en"}],"detectedBreak":{"type":"EOL_SURE_SPACE"}},"boundingBox":{"vertices":[{"x":460,"y":167},{"x":474,"y":167},{"x":474,"y":193},{"x":460,"y":193}]},"text":"E"}]}]}],"blockType":"TEXT"},{"property":{"detectedLanguages":[{"languageCode":"en","confidence":1}]},"boundingBox":{"vertices":[{"x":348,"y":211},{"x":506,"y":211},{"x":506,"y":237},{"x":348,"y":237}]},"paragraphs":[{"property":{"detectedLanguages":[{"languageCode":"en","confidence":1}]},"boundingBox":{"vertices":[{"x":348,"y":211},{"x":506,"y":211},{"x":506,"y":237},{"x":348,"y":237}]},"words":[{"property":{"detectedLanguages":[{"languageCode":"en"}]},"boundingBox":{"vertices":[{"x":348,"y":211},{"x":506,"y":211},{"x":506,"y":237},{"x":348,"y":237}]},"symbols":[{"property":{"detectedLanguages":[{"languageCode":"en"}]},"boundingBox":{"vertices":[{"x":348,"y":211},{"x":368,"y":211},{"x":368,"y":237},{"x":348,"y":237}]},"text":"W"},{"property":{"detectedLanguages":[{"languageCode":"en"}]},"boundingBox":{"vertices":[{"x":378,"y":211},{"x":393,"y":211},{"x":393,"y":237},{"x":378,"y":237}]},"text":"H"},{"property":{"detectedLanguages":[{"languageCode":"en"}]},"boundingBox":{"vertices":[{"x":406,"y":211},{"x":410,"y":211},{"x":410,"y":237},{"x":406,"y":237}]},"text":"I"},{"property":{"detectedLanguages":[{"languageCode":"en"}]},"boundingBox":{"vertices":[{"x":421,"y":211},{"x":436,"y":211},{"x":436,"y":237},{"x":421,"y":237}]},"text":"S"},{"property":{"detectedLanguages":[{"languageCode":"en"}]},"boundingBox":{"vertices":[{"x":444,"y":211},{"x":459,"y":211},{"x":459,"y":237},{"x":444,"y":237}]},"text":"P"},{"property":{"detectedLanguages":[{"languageCode":"en"}]},"boundingBox":{"vertices":[{"x":467,"y":212},{"x":481,"y":212},{"x":481,"y":237},{"x":467,"y":237}]},"text":"E"},{"property":{"detectedLanguages":[{"languageCode":"en"}],"detectedBreak":{"type":"EOL_SURE_SPACE"}},"boundingBox":{"vertices":[{"x":492,"y":211},{"x":506,"y":211},{"x":506,"y":237},{"x":492,"y":237}]},"text":"R"}]}]}],"blockType":"TEXT"},{"property":{"detectedLanguages":[{"languageCode":"en","confidence":1}]},"boundingBox":{"vertices":[{"x":368,"y":255},{"x":488,"y":255},{"x":488,"y":281},{"x":368,"y":281}]},"paragraphs":[{"property":{"detectedLanguages":[{"languageCode":"en","confidence":1}]},"boundingBox":{"vertices":[{"x":368,"y":255},{"x":488,"y":255},{"x":488,"y":281},{"x":368,"y":281}]},"words":[{"property":{"detectedLanguages":[{"languageCode":"en"}]},"boundingBox":{"vertices":[{"x":368,"y":255},{"x":488,"y":255},{"x":488,"y":281},{"x":368,"y":281}]},"symbols":[{"property":{"detectedLanguages":[{"languageCode":"en"}]},"boundingBox":{"vertices":[{"x":368,"y":255},{"x":384,"y":255},{"x":384,"y":281},{"x":368,"y":281}]},"text":"A"},{"property":{"detectedLanguages":[{"languageCode":"en"}]},"boundingBox":{"vertices":[{"x":396,"y":255},{"x":410,"y":255},{"x":410,"y":281},{"x":396,"y":281}]},"text":"F"},{"property":{"detectedLanguages":[{"languageCode":"en"}]},"boundingBox":{"vertices":[{"x":419,"y":255},{"x":435,"y":255},{"x":435,"y":281},{"x":419,"y":281}]},"text":"T"},{"property":{"detectedLanguages":[{"languageCode":"en"}]},"boundingBox":{"vertices":[{"x":446,"y":255},{"x":460,"y":255},{"x":460,"y":281},{"x":446,"y":281}]},"text":"E"},{"property":{"detectedLanguages":[{"languageCode":"en"}],"detectedBreak":{"type":"EOL_SURE_SPACE"}},"boundingBox":{"vertices":[{"x":474,"y":255},{"x":488,"y":255},{"x":488,"y":281},{"x":474,"y":281}]},"text":"R"}]}]}],"blockType":"TEXT"},{"property":{"detectedLanguages":[{"languageCode":"en","confidence":1}]},"boundingBox":{"vertices":[{"x":341,"y":304},{"x":513,"y":303},{"x":513,"y":338},{"x":341,"y":339}]},"paragraphs":[{"property":{"detectedLanguages":[{"languageCode":"en","confidence":1}]},"boundingBox":{"vertices":[{"x":341,"y":304},{"x":513,"y":303},{"x":513,"y":338},{"x":341,"y":339}]},"words":[{"property":{"detectedLanguages":[{"languageCode":"en"}]},"boundingBox":{"vertices":[{"x":341,"y":309},{"x":402,"y":309},{"x":402,"y":335},{"x":341,"y":335}]},"symbols":[{"property":{"detectedLanguages":[{"languageCode":"en"}]},"boundingBox":{"vertices":[{"x":341,"y":309},{"x":356,"y":309},{"x":356,"y":334},{"x":341,"y":334}]},"text":"T"},{"property":{"detectedLanguages":[{"languageCode":"en"}]},"boundingBox":{"vertices":[{"x":363,"y":309},{"x":377,"y":309},{"x":377,"y":334},{"x":363,"y":334}]},"text":"H"},{"property":{"detectedLanguages":[{"languageCode":"en"}],"detectedBreak":{"type":"SPACE"}},"boundingBox":{"vertices":[{"x":388,"y":309},{"x":402,"y":309},{"x":402,"y":335},{"x":388,"y":335}]},"text":"E"}]},{"property":{"detectedLanguages":[{"languageCode":"en"}]},"boundingBox":{"vertices":[{"x":423,"y":304},{"x":513,"y":303},{"x":513,"y":337},{"x":423,"y":338}]},"symbols":[{"property":{"detectedLanguages":[{"languageCode":"en"}]},"boundingBox":{"vertices":[{"x":423,"y":304},{"x":443,"y":304},{"x":443,"y":338},{"x":423,"y":338}]},"text":"N"},{"property":{"detectedLanguages":[{"languageCode":"en"}]},"boundingBox":{"vertices":[{"x":444,"y":304},{"x":461,"y":304},{"x":461,"y":338},{"x":444,"y":338}]},"text":"O"},{"property":{"detectedLanguages":[{"languageCode":"en"}]},"boundingBox":{"vertices":[{"x":462,"y":304},{"x":478,"y":304},{"x":478,"y":338},{"x":462,"y":338}]},"text":"I"},{"property":{"detectedLanguages":[{"languageCode":"en"}]},"boundingBox":{"vertices":[{"x":479,"y":304},{"x":496,"y":304},{"x":496,"y":338},{"x":479,"y":338}]},"text":"S"},{"property":{"detectedLanguages":[{"languageCode":"en"}],"detectedBreak":{"type":"EOL_SURE_SPACE"}},"boundingBox":{"vertices":[{"x":497,"y":304},{"x":513,"y":304},{"x":513,"y":338},{"x":497,"y":338}]},"text":"E"}]}]}],"blockType":"TEXT"}]}],"text":"HIS VOICE\nIS THE\nWHISPER\nAFTER\nTHE NOISE\n"}}]}
