{"responses":[{"labelAnnotations":[{"mid":"/m/09ddx","description":"Duck","score":0.93785632,"topicality":0.93785632},{"mid":"/m/01bqvp","description":"Sky","score":0.93361944,"topicality":0.93361944},{"mid":"/m/015p6","description":"Bird","score":0.92427248,"topicality":0.92427248},{"mid":"/m/08t9c_","description":"Grass","score":0.91006476,"topicality":0.91006476},{"mid":"/m/0838f","description":"Water","score":0.91002715,"topicality":0.91002715},{"mid":"/m/023bbt","description":"Wilderness","score":0.90519452,"topicality":0.90519452},{"mid":"/m/0gg8brk","description":"Water bird","score":0.8988471,"topicality":0.8988471},{"mid":"/m/02py09","description":"Natural environment","score":0.8843857,"topicality":0.8843857},{"mid":"/m/07j7r","description":"Tree","score":0.8723194,"topicality":0.8723194},{"mid":"/m/09d_r","description":"Mountain","score":0.85521019,"topicality":0.85521019}]}]}
