{"responses":[{"labelAnnotations":[{"mid":"/m/01yrx","description":"Cat","score":0.92428124,"topicality":0.92428124},{"mid":"/m/05c1ypb","description":"Nap","score":0.86284685,"topicality":0.86284685},{"mid":"/m/04f6rz","description":"Turquoise","score":0.86235338,"topicality":0.86235338},{"mid":"/m/0c_jw","description":"Furniture","score":0.84273905,"topicality":0.84273905},{"mid":"/m/06ht1","description":"Room","score":0.83105171,"topicality":0.83105171},{"mid":"/m/02_ktj","description":"Morning","score":0.81413555,"topicality":0.81413555},{"mid":"/m/02crq1","description":"Couch","score":0.79359144,"topicality":0.79359144},{"mid":"/m/0307l","description":"Felidae","score":0.76134771,"topicality":0.76134771},{"mid":"/m/0dnr7","description":"Textile","score":0.72930312,"topicality":0.72930312},{"mid":"/m/08xgn7","description":"Comfort","score":0.72170979,"topicality":0.72170979}]}]}
