{"responses":[{"faceAnnotations":[{"boundingPoly":{"vertices":[{"x":128,"y":172},{"x":349,"y":172},{"x":349,"y":429},{"x":128,"y":429}]},"fdBoundingPoly":{"vertices":[{"x":145,"y":219},{"x":338,"y":219},{"x":338,"y":412},{"x":145,"y":412}]},"landmarks":[{"type":"LEFT_EYE","position":{"x":247.2951,"y":285.83871,"z":-0.0015241392}},{"type":"RIGHT_EYE","position":{"x":301.21567,"y":272.4054,"z":46.51247}},{"type":"LEFT_OF_LEFT_EYEBROW","position":{"x":226.35168,"y":275.37689,"z":-7.6894441}},{"type":"RIGHT_OF_LEFT_EYEBROW","position":{"x":266.09232,"y":265.1673,"z":3.5614533}},{"type":"LEFT_OF_RIGHT_EYEBROW","position":{"x":288.98871,"y":259.95633,"z":24.16452}},{"type":"RIGHT_OF_RIGHT_EYEBROW","position":{"x":305.10745,"y":257.15854,"z":63.619247}},{"type":"MIDPOINT_BETWEEN_EYES","position":{"x":283.97748,"y":274.99188,"z":12.648244}},{"type":"NOSE_TIP","position":{"x":303.75989,"y":305.76654,"z":-2.507175}},{"type":"UPPER_LIP","position":{"x":299.06705,"y":332.43164,"z":8.2286148}},{"type":"LOWER_LIP","position":{"x":301.12134,"y":354.58737,"z":11.109425}},{"type":"MOUTH_LEFT","position":{"x":266.37598,"y":351.1001,"z":4.0857997}},{"type":"MOUTH_RIGHT","position":{"x":309.24533,"y":339.55847,"z":38.206345}},{"type":"MOUTH_CENTER","position":{"x":298.72705,"y":343.42194,"z":11.54687}},{"type":"NOSE_BOTTOM_RIGHT","position":{"x":301.7486,"y":312.99783,"z":28.229313}},{"type":"NOSE_BOTTOM_LEFT","position":{"x":276.46323,"y":317.45789,"z":4.7124848}},{"type":"NOSE_BOTTOM_CENTER","position":{"x":297.39349,"y":317.25208,"z":8.2926111}},{"type":"LEFT_EYE_TOP_BOUNDARY","position":{"x":251.55167,"y":280.13123,"z":-1.6379046}},{"type":"LEFT_EYE_RIGHT_CORNER","position":{"x":258.53867,"y":284.64648,"z":10.048002}},{"type":"LEFT_EYE_BOTTOM_BOUNDARY","position":{"x":248.05432,"y":291.09097,"z":0.55922282}},{"type":"LEFT_EYE_LEFT_CORNER","position":{"x":235.65372,"y":289.09262,"z":-2.5994236}},{"type":"LEFT_EYE_PUPIL","position":{"x":250.22411,"y":285.08008,"z":-0.19627336}},{"type":"RIGHT_EYE_TOP_BOUNDARY","position":{"x":298.78934,"y":269.17245,"z":40.862408}},{"type":"RIGHT_EYE_RIGHT_CORNER","position":{"x":302.78906,"y":273.323,"z":57.231018}},{"type":"RIGHT_EYE_BOTTOM_BOUNDARY","position":{"x":302.22379,"y":277.39166,"z":44.11277}},{"type":"RIGHT_EYE_LEFT_CORNER","position":{"x":290.78815,"y":276.23972,"z":36.601147}},{"type":"RIGHT_EYE_PUPIL","position":{"x":298.60388,"y":273.82812,"z":43.263535}},{"type":"LEFT_EYEBROW_UPPER_MIDPOINT","position":{"x":246.82794,"y":261.94202,"z":-5.2835689}},{"type":"RIGHT_EYEBROW_UPPER_MIDPOINT","position":{"x":297.94553,"y":250.16141,"z":40.843967}},{"type":"LEFT_EAR_TRAGION","position":{"x":164.91676,"y":339.1521,"z":35.028015}},{"type":"RIGHT_EAR_TRAGION","position":{"x":283.69916,"y":311.94125,"z":132.40402}},{"type":"FOREHEAD_GLABELLA","position":{"x":279.01047,"y":261.32062,"z":11.978168}},{"type":"CHIN_GNATHION","position":{"x":303.08917,"y":384.26782,"z":17.010534}},{"type":"CHIN_LEFT_GONION","position":{"x":201.43047,"y":377.29712,"z":17.672974}},{"type":"CHIN_RIGHT_GONION","position":{"x":304.14185,"y":348.7041,"z":110.72759}}],"rollAngle":-14.555286,"panAngle":41.381721,"tiltAngle":1.639256,"detectionConfidence":0.71425575,"landmarkingConfidence":0.57522404,"joyLikelihood":"UNLIKELY","sorrowLikelihood":"VERY_UNLIKELY","angerLikelihood":"VERY_UNLIKELY","surpriseLikelihood":"VERY_UNLIKELY","underExposedLikelihood":"VERY_UNLIKELY","blurredLikelihood":"VERY_UNLIKELY","headwearLikelihood":"VERY_UNLIKELY"}],"labelAnnotations":[{"mid":"/m/0dzct","description":"Face","score":0.95382673,"topicality":0.95382673},{"mid":"/m/0ytgt","description":"Child","score":0.91898268,"topicality":0.91898268},{"mid":"/m/01jwgf","description":"Product","score":0.91031128,"topicality":0.91031128},{"mid":"/m/04hgtk","description":"Head","score":0.89474082,"topicality":0.89474082},{"mid":"/m/06z04","description":"Skin","score":0.88113898,"topicality":0.88113898},{"mid":"/m/01bgsw","description":"Toddler","score":0.86049312,"topicality":0.86049312},{"mid":"/m/01f43","description":"Beauty","score":0.85963929,"topicality":0.85963929},{"mid":"/m/03mcr3","description":"Bedding","score":0.84561157,"topicality":0.84561157},{"mid":"/m/01fklc","description":"Pink","score":0.81467903,"topicality":0.81467903},{"mid":"/m/0c_jw","description":"Furniture","score":0.80554765,"topicality":0.80554765}]}]}
